pyparticle/README.md
pyparticle/__init__.py
pyparticle/_patch.py
pyparticle/aerosol_particle.py
pyparticle/constants.py
pyparticle/data.py
pyparticle/utilities.py
pyparticle/analysis/README.md
pyparticle/analysis/__init__.py
pyparticle/analysis/base.py
pyparticle/analysis/builder.py
pyparticle/analysis/defaults.py
pyparticle/analysis/distributions.py
pyparticle/analysis/global_registry.py
pyparticle/analysis/registry.py
pyparticle/analysis/particle/__init__.py
pyparticle/analysis/particle/base.py
pyparticle/analysis/particle/factory/Dwet.py
pyparticle/analysis/particle/factory/P_frz.py
pyparticle/analysis/particle/factory/kappa.py
pyparticle/analysis/particle/factory/registry.py
pyparticle/analysis/population/__init__.py
pyparticle/analysis/population/base.py
pyparticle/analysis/population/factory/Nccn.py
pyparticle/analysis/population/factory/T_grid.py
pyparticle/analysis/population/factory/avg_Jhet.py
pyparticle/analysis/population/factory/b_abs.py
pyparticle/analysis/population/factory/b_ext.py
pyparticle/analysis/population/factory/b_scat.py
pyparticle/analysis/population/factory/dNdlnD.py
pyparticle/analysis/population/factory/dNdlnD_old.py
pyparticle/analysis/population/factory/diam_grid.py
pyparticle/analysis/population/factory/frac_ccn.py
pyparticle/analysis/population/factory/frozen_frac.py
pyparticle/analysis/population/factory/nucleating_sites.py
pyparticle/analysis/population/factory/registry.py
pyparticle/analysis/population/factory/rh_grid.py
pyparticle/analysis/population/factory/s_grid.py
pyparticle/analysis/population/factory/spec_mass_conc.py
pyparticle/analysis/population/factory/wvl_grid.py
pyparticle/datasets/model_output/mam4/fort.130
pyparticle/datasets/model_output/mam4/fort.150
pyparticle/datasets/model_output/mam4/fort.30
pyparticle/datasets/model_output/mam4/fort.82
pyparticle/datasets/model_output/mam4/fort.90
pyparticle/datasets/model_output/mam4/fort.91
pyparticle/datasets/model_output/mam4/fort.92
pyparticle-0.1.1.dist-info/licenses/LICENSE
pyparticle-0.1.1.dist-info/METADATA
pyparticle-0.1.1.dist-info/WHEEL
pyparticle-0.1.1.dist-info/top_level.txt
pyparticle-0.1.1.dist-info/RECORD
