Metadata-Version: 2.4
Name: pyparticle
Version: 0.1.1
Summary: Describing and analyzing aerosol particles and particle populations
Author: Laura Fierce
License: MIT License
Project-URL: Repository, https://github.com/pnnl/pyparticle
Keywords: aerosol,atmospheric,optics,modeling
Classifier: License :: OSI Approved :: MIT License
Classifier: Programming Language :: Python :: 3 :: Only
Classifier: Programming Language :: Python :: 3.9
Classifier: Programming Language :: Python :: 3.10
Classifier: Programming Language :: Python :: 3.11
Classifier: Programming Language :: Python :: 3.12
Classifier: Intended Audience :: Science/Research
Classifier: Topic :: Scientific/Engineering
Requires-Python: >=3.9
License-File: LICENSE
Requires-Dist: numpy>=1.24
Requires-Dist: scipy>=1.10
Requires-Dist: PyYAML>=6.0
Requires-Dist: pymiescatt
Requires-Dist: netCDF4
Provides-Extra: dev
Requires-Dist: ruff>=0.5; extra == "dev"
Requires-Dist: mypy>=1.8; extra == "dev"
Requires-Dist: pytest>=7.0; extra == "dev"
Requires-Dist: pytest-cov>=4.0; extra == "dev"
Requires-Dist: pyrcel>=0.4; extra == "dev"
Dynamic: license-file
